odoo8_addon_l10n_br_sale_service-8.0.1.0.0.99.dev6-py2.7-nspkg.pth
odoo_addons/l10n_br_sale_service/__openerp__.py
odoo_addons/l10n_br_sale_service/__init__.py
odoo_addons/l10n_br_sale_service/README.rst
odoo_addons/l10n_br_sale_service/models/sale.py
odoo_addons/l10n_br_sale_service/models/__init__.py
odoo_addons/l10n_br_sale_service/i18n/pt_BR.po
odoo_addons/l10n_br_sale_service/tests/test_sale_order_service.py
odoo_addons/l10n_br_sale_service/tests/__init__.py
odoo_addons/l10n_br_sale_service/static/description/icon.png
odoo8_addon_l10n_br_sale_service-8.0.1.0.0.99.dev6.dist-info/top_level.txt
odoo8_addon_l10n_br_sale_service-8.0.1.0.0.99.dev6.dist-info/WHEEL
odoo8_addon_l10n_br_sale_service-8.0.1.0.0.99.dev6.dist-info/RECORD
odoo8_addon_l10n_br_sale_service-8.0.1.0.0.99.dev6.dist-info/metadata.json
odoo8_addon_l10n_br_sale_service-8.0.1.0.0.99.dev6.dist-info/DESCRIPTION.rst
odoo8_addon_l10n_br_sale_service-8.0.1.0.0.99.dev6.dist-info/METADATA
odoo8_addon_l10n_br_sale_service-8.0.1.0.0.99.dev6.dist-info/namespace_packages.txt
